<?xml version="1.0" encoding="UTF-8" standalone="yes"?><javaScriptFFIContainer><namespaces name="maps"><jsClasses xmlns:xsi="http://www.w3.org/2001/XMLSchema-instance" xsi:type="javaScriptRCCustomWidget"><constructors/><jsMethods name="clear"><mappings platformId="8"><nativeMethod className="CustomMapWidget" frameworks="" library="" name="clear" packageName="" static="false"><versionSpecificLibraries><entry><key>5.0</key></entry><entry><key>6.0</key></entry></versionSpecificLibraries></nativeMethod></mappings><mappings platformId="18"><nativeMethod className="CustomMapWidget" frameworks="" library="" name="clear" packageName="" static="false"><versionSpecificLibraries><entry><key>5.0</key></entry><entry><key>6.0</key></entry></versionSpecificLibraries></nativeMethod></mappings><returnTypes>void</returnTypes></jsMethods><jsMethods name="dismissCallout"><mappings platformId="8"><nativeMethod className="CustomMapWidget" frameworks="" library="" name="dismissCallout" packageName="" static="false"><params dataType="java.util.Hashtable"/><versionSpecificLibraries><entry><key>5.0</key></entry><entry><key>6.0</key></entry></versionSpecificLibraries></nativeMethod></mappings><mappings platformId="18"><nativeMethod className="CustomMapWidget" frameworks="" library="" name="dismissCallout" packageName="" static="false"><params dataType="java.util.Hashtable"/><versionSpecificLibraries><entry><key>5.0</key></entry><entry><key>6.0</key></entry></versionSpecificLibraries></nativeMethod></mappings><params dataType="Object" name="location"/><returnTypes>void</returnTypes></jsMethods><jsMethods name="animateToLocation"><mappings platformId="8"><nativeMethod className="CustomMapWidget" frameworks="" library="" name="animateToLocation" packageName="" static="false"><params dataType="java.util.Hashtable"/><versionSpecificLibraries><entry><key>5.0</key></entry><entry><key>6.0</key></entry></versionSpecificLibraries></nativeMethod></mappings><mappings platformId="18"><nativeMethod className="CustomMapWidget" frameworks="" library="" name="animateToLocation" packageName="" static="false"><params dataType="java.util.Hashtable"/><versionSpecificLibraries><entry><key>5.0</key></entry><entry><key>6.0</key></entry></versionSpecificLibraries></nativeMethod></mappings><params dataType="Object" name="location"/><returnTypes>void</returnTypes></jsMethods><jsMethods name="navigateToIndex"><mappings platformId="8"><nativeMethod className="CustomMapWidget" frameworks="" library="" name="navigateToIndex" packageName="" static="false"><params dataType="int"/><params dataType="boolean"/><versionSpecificLibraries><entry><key>5.0</key></entry><entry><key>6.0</key></entry></versionSpecificLibraries></nativeMethod></mappings><mappings platformId="18"><nativeMethod className="CustomMapWidget" frameworks="" library="" name="navigateToIndex" packageName="" static="false"><params dataType="int"/><params dataType="boolean"/><versionSpecificLibraries><entry><key>5.0</key></entry><entry><key>6.0</key></entry></versionSpecificLibraries></nativeMethod></mappings><params dataType="Number" name="index"/><params dataType="Boolean" name="showcallout"/><returnTypes>void</returnTypes></jsMethods><mappings platformId="8"><nativeClasses xsi:type="jsCustomWidgetNativeClass" frameworks="" library="CustomMapWidgetLib.jar" name="" packageName="com.customwidgets.maps"><constructors constructor="true" name="CustomMapWidget" static="true"/><versionSpecificLibraries><entry><key>5.0</key></entry><entry><key>6.0</key></entry></versionSpecificLibraries><eventDelegateProtocol></eventDelegateProtocol><widgetClassName>CustomMapWidget</widgetClassName></nativeClasses></mappings><mappings platformId="18"><nativeClasses xsi:type="jsCustomWidgetNativeClass" frameworks="" library="CustomMapWidgetLib.jar" name="" packageName="com.customwidgets.maps"><constructors constructor="true" name="CustomMapWidget" static="true"/><versionSpecificLibraries><entry><key>5.0</key></entry><entry><key>6.0</key></entry></versionSpecificLibraries><eventDelegateProtocol></eventDelegateProtocol><widgetClassName>CustomMapWidget</widgetClassName></nativeClasses></mappings><name>CustomMapWidget</name><id>jsRCCustomWidget118198246453449</id><properties><customProperties dataType="String" name="displayMode"><categoryType></categoryType><defaultValue><optionsList>Normal</optionsList><optionsList>Satellite</optionsList><optionsList>Traffic</optionsList></defaultValue><id>jsRCCustomProperty118198246453450</id><ideType>List</ideType><isProgrammable>true</isProgrammable><mappings><library></library><nativeProperty><nativeType>java.lang.String</nativeType><returnType>java.lang.String</returnType></nativeProperty><platformId>8</platformId></mappings><mappings><library></library><nativeProperty><nativeType>java.lang.String</nativeType><returnType>java.lang.String</returnType></nativeProperty><platformId>18</platformId></mappings></customProperties><customProperties dataType="Number" name="zoomLevel"><categoryType></categoryType><defaultValue><stringValue>1</stringValue></defaultValue><id>jsRCCustomProperty118198246453451</id><ideType>Number</ideType><isProgrammable>true</isProgrammable><mappings><library></library><nativeProperty><nativeType>int</nativeType><returnType>int</returnType></nativeProperty><platformId>8</platformId></mappings><mappings><library></library><nativeProperty><nativeType>int</nativeType><returnType>int</returnType></nativeProperty><platformId>18</platformId></mappings></customProperties><customProperties dataType="Boolean" name="showZoomControl"><categoryType></categoryType><defaultValue><boolValue>true</boolValue></defaultValue><id>jsRCCustomProperty118198246453452</id><ideType>Boolean</ideType><isProgrammable>false</isProgrammable><mappings><library></library><nativeProperty><nativeType>boolean</nativeType><returnType>boolean</returnType></nativeProperty><platformId>8</platformId></mappings><mappings><library></library><nativeProperty><nativeType>boolean</nativeType><returnType>boolean</returnType></nativeProperty><platformId>18</platformId></mappings></customProperties><customProperties dataType="Number" name="width"><categoryType></categoryType><defaultValue><stringValue>100</stringValue></defaultValue><id>jsRCCustomProperty118198246453453</id><ideType>Number</ideType><isProgrammable>false</isProgrammable><mappings><library></library><nativeProperty><nativeType>int</nativeType><returnType>int</returnType></nativeProperty><platformId>8</platformId></mappings><mappings><library></library><nativeProperty><nativeType>int</nativeType><returnType>int</returnType></nativeProperty><platformId>18</platformId></mappings></customProperties><customProperties dataType="Number" name="height"><categoryType></categoryType><defaultValue><stringValue>75</stringValue></defaultValue><id>jsRCCustomProperty118198246453454</id><ideType>Number</ideType><isProgrammable>false</isProgrammable><mappings><library></library><nativeProperty><nativeType>int</nativeType><returnType>int</returnType></nativeProperty><platformId>8</platformId></mappings><mappings><library></library><nativeProperty><nativeType>int</nativeType><returnType>int</returnType></nativeProperty><platformId>18</platformId></mappings></customProperties><customProperties dataType="Function" name="onPinClick"><categoryType>Event</categoryType><defaultValue><eventRoot><evtSequence><enabled>true</enabled><seqname></seqname></evtSequence></eventRoot></defaultValue><eventParamList><paramName>address</paramName></eventParamList><id>jsRCCustomProperty118198246453478</id><ideType>Event</ideType><isProgrammable>false</isProgrammable><mappings><library></library><nativeProperty><nativeType>com.konylabs.vm.Function</nativeType><returnType>com.konylabs.vm.Function</returnType></nativeProperty><platformId>8</platformId></mappings><mappings><library></library><nativeProperty><nativeType>com.konylabs.vm.Function</nativeType><returnType>com.konylabs.vm.Function</returnType></nativeProperty><platformId>18</platformId></mappings></customProperties><customProperties dataType="Function" name="onMapClick"><categoryType>Event</categoryType><defaultValue><eventRoot><evtSequence><enabled>true</enabled><seqname></seqname></evtSequence></eventRoot></defaultValue><eventParamList><paramName>location</paramName></eventParamList><id>jsRCCustomProperty118198246453479</id><ideType>Event</ideType><isProgrammable>false</isProgrammable><mappings><library></library><nativeProperty><nativeType>com.konylabs.vm.Function</nativeType><returnType>com.konylabs.vm.Function</returnType></nativeProperty><platformId>8</platformId></mappings><mappings><library></library><nativeProperty><nativeType>com.konylabs.vm.Function</nativeType><returnType>com.konylabs.vm.Function</returnType></nativeProperty><platformId>18</platformId></mappings></customProperties><customProperties dataType="Function" name="onBoundsChange"><categoryType>Event</categoryType><defaultValue><eventRoot><evtSequence><enabled>true</enabled><seqname></seqname></evtSequence></eventRoot></defaultValue><eventParamList><paramName>bounds</paramName></eventParamList><id>jsRCCustomProperty118198246453480</id><ideType>Event</ideType><isProgrammable>false</isProgrammable><mappings><library></library><nativeProperty><nativeType>com.konylabs.vm.Function</nativeType><returnType>com.konylabs.vm.Function</returnType></nativeProperty><platformId>8</platformId></mappings><mappings><library></library><nativeProperty><nativeType>com.konylabs.vm.Function</nativeType><returnType>com.konylabs.vm.Function</returnType></nativeProperty><platformId>18</platformId></mappings></customProperties><customProperties dataType="Array" name="locationData"><categoryType></categoryType><id>jsRCCustomProperty156334898458138</id><ideType>Not Applicable</ideType><isProgrammable>true</isProgrammable><mappings><library></library><nativeProperty><nativeType>java.util.Vector</nativeType><returnType>java.util.Vector</returnType></nativeProperty><platformId>8</platformId></mappings><mappings><library></library><nativeProperty><nativeType>java.util.Vector</nativeType><returnType>java.util.Vector</returnType></nativeProperty><platformId>18</platformId></mappings></customProperties><customProperties dataType="Object" name="address"><categoryType></categoryType><id>jsRCCustomProperty118186330058139</id><ideType>Not Applicable</ideType><isProgrammable>true</isProgrammable><mappings><library></library><nativeProperty><nativeType>java.util.Hashtable</nativeType><returnType>java.util.Hashtable</returnType></nativeProperty><platformId>8</platformId></mappings><mappings><library></library><nativeProperty><nativeType>java.util.Hashtable</nativeType><returnType>java.util.Hashtable</returnType></nativeProperty><platformId>18</platformId></mappings></customProperties></properties></jsClasses></namespaces></javaScriptFFIContainer>